{
  "hero_title": "Pamonhas Mil",
  "hero_content": "<p><strong>O sabor da pamonha que une gerações, da nossa família para a sua.</strong></p><p>Desde o milho fresquinho até a pamonha quentinha saindo da palha, nossa tradição familiar existe para criar momentos especiais na sua. Queremos fazer parte do seu café da tarde, do seu almoço de domingo e das suas melhores memórias.</p>",
  "services_title": "Nossa história",
  "clients_title": "Essas empresas confiam no nosso trabalho",
  "testimonials_title": "Clientes ♥ nós",
  "case_studies_title": "Cardápio",
  "pricing_title": "We do design retainers",
  "quote_content": "This <strong>design agency</strong> is a <strong>game changer</strong>. Its <strong>creative vision</strong>, <strong>user-focused approach</strong>, and <strong>seamless collaboration</strong> have <strong>transformed</strong> the way we <strong>build our brand</strong>. It’s <strong>not just an agency</strong> — it’s a <strong>powerful partner</strong> that <strong>delivers real results</strong>.",
  "quote_cite": "Sean Higgins",
  "quote_role": "CTO, Interia",
  "quote_image": "/content-images/quote-man.avif",
  "faq_title": "Frequently Asked Questions"
}